explosive.fuse-0.5-py3.5-nspkg.pth
explosive/fuse/__init__.py
explosive/fuse/_rarfile.py
explosive/fuse/archive.py
explosive/fuse/ctrl.py
explosive/fuse/exception.py
explosive/fuse/fs.py
explosive/fuse/mapper.py
explosive/fuse/pathmaker.py
explosive.fuse-0.5.dist-info/METADATA
explosive.fuse-0.5.dist-info/RECORD
explosive.fuse-0.5.dist-info/WHEEL
explosive.fuse-0.5.dist-info/entry_points.txt
explosive.fuse-0.5.dist-info/namespace_packages.txt
explosive.fuse-0.5.dist-info/top_level.txt
