Metadata-Version: 2.1
Name: explosive.fuse
Version: 0.5
Summary: Mount archives as a filesystem.
Home-page: https://github.com/metatoaster/explosive.fuse
Author: Tommy Yu
Author-email: y@metatoaster.com
License: GPL
Platform: UNKNOWN
Classifier: Development Status :: 4 - Beta
Classifier: Intended Audience :: Developers
Classifier: Intended Audience :: End Users/Desktop
Classifier: Operating System :: MacOS :: MacOS X
Classifier: Operating System :: POSIX :: Linux
Classifier: Programming Language :: Python
Classifier: Programming Language :: Python :: 2.7
Classifier: Programming Language :: Python :: 3.3
Classifier: Programming Language :: Python :: 3.4
Classifier: Programming Language :: Python :: 3.5
Classifier: Programming Language :: Python :: Implementation :: PyPy
Classifier: License :: OSI Approved :: GNU General Public License v3 or later (GPLv3+)
Classifier: Topic :: System :: Filesystems
Requires-Dist: setuptools
Requires-Dist: fusepy
